auto_openvpn-1.0.6.dist-info/METADATA
auto_openvpn-1.0.6.dist-info/RECORD
auto_openvpn-1.0.6.dist-info/WHEEL
auto_openvpn-1.0.6.dist-info/entry_points.txt
auto_openvpn-1.0.6.dist-info/top_level.txt
openvpn/__init__.py
openvpn/makeIt.py
tests/__init__.py
tests/test_contri.py
