Metadata-Version: 2.1
Name: auto-openvpn
Version: 1.0.6
Summary: One command OpenVPN free account
Home-page: https://github.com/aashutoshrathi/auto-openvpn
Author: Aashutosh Rathi
Author-email: aashutoshrathi@gmail.com
License: UNKNOWN
Platform: UNKNOWN
Classifier: Programming Language :: Python :: 3
Classifier: License :: OSI Approved :: MIT License
Classifier: Operating System :: OS Independent
Requires-Dist: selenium
Requires-Dist: pyperclip
